dolphin_models/DecisionTree_scr.py
dolphin_models/KNN_scr.py
dolphin_models/LinearRegression_scr.py
dolphin_models/LogisticRegression_scr.py
dolphin_models/MultipleRegression_scr.py
dolphin_models/RandomForest_scr.py
dolphin_models/__init__.py
dolphin_models/main.py
tests/__init__.py
tests/test_DecisionTree.py
tests/test_KNN.py
tests/test_LinearRegression.py
tests/test_LogisticRegression.py
tests/test_MultipleRegression.py
tests/test_RandomForest.py
dolphin_models-0.1.0.dist-info/LICENSE
dolphin_models-0.1.0.dist-info/METADATA
dolphin_models-0.1.0.dist-info/WHEEL
dolphin_models-0.1.0.dist-info/top_level.txt
dolphin_models-0.1.0.dist-info/RECORD
