Metadata-Version: 2.1
Name: dolphin_models
Version: 0.1.0
Summary: A Python package implementing popular machine learning models.
Author: Surieya
Author-email: Surieya <surieyasurieya@gmail.com>
License: MIT License
Requires-Python: >=3.6
License-File: LICENSE
